aiovkmusic_x/.gitignore
aiovkmusic_x/__init__.py
aiovkmusic_x/audio.py
aiovkmusic_x/audio_url_decoder.py
aiovkmusic_x/base.py
aiovkmusic_x/enums.py
aiovkmusic_x/exceptions.py
aiovkmusic_x/jconfig.py
aiovkmusic_x/memory.py
aiovkmusic_x/model.py
aiovkmusic_x/music.py
aiovkmusic_x/session.py
aiovkmusic_x/utils.py
aiovkmusic_x/vk_api.py
aiovkmusic_x-1.6.8.3.dist-info/WHEEL
aiovkmusic_x-1.6.8.3.dist-info/METADATA
aiovkmusic_x-1.6.8.3.dist-info/RECORD
