Metadata-Version: 2.1
Name: aiovkmusic_x
Version: 1.6.8.3
Summary: aiovkmusic_x
Author-email: lavacat <steveharris2828@gmail.com>
Requires-Python: >=3.6
Requires-Dist: python-ffmpeg
Requires-Dist: loguru
Requires-Dist: bs4
Requires-Dist: asyncio
Project-URL: Source, https://codeberg.org/agark0vlad21/aiovkmusic-x
